receipt_print/__init__.py
receipt_print/cli.py
receipt_print-0.0.1.dist-info/METADATA
receipt_print-0.0.1.dist-info/WHEEL
receipt_print-0.0.1.dist-info/entry_points.txt
receipt_print-0.0.1.dist-info/top_level.txt
receipt_print-0.0.1.dist-info/RECORD
