Metadata-Version: 2.2
Name: receipt-print
Version: 0.0.1
Summary: receipt printer CLI
Author: jmpaz
Project-URL: Homepage, https://github.com/jmpaz/receipt-print
Requires-Python: >=3.11
Requires-Dist: python-escpos>=3.1
Requires-Dist: pyusb>=1.3.1
